[{"id":1,"empresa":"SHELL CAPSA"},{"id":2,"empresa":"ORVOL"},{"id":3,"empresa":"YPF"},{"id":5,"empresa":"DAPSA"},{"id":6,"empresa":"PETROBRAS"},{"id":7,"empresa":"EXOLGAN"},{"id":8,"empresa":"LOGINTER S.A."},{"id":9,"empresa":"TRANSPORTES FLUVIALES JILGUERO"},{"id":10,"empresa":"PETRORIO"},{"id":11,"empresa":"TAGSA"},{"id":12,"empresa":"DECOSUR"},{"id":13,"empresa":"JILGUERO"},{"id":14,"empresa":"HAPAG LLOYD"},{"id":15,"empresa":"BLINKI"},{"id":16,"empresa":"ULTRAMAR"},{"id":17,"empresa":"CSAV"},{"id":18,"empresa":"MSC"},{"id":19,"empresa":"DELFINO"},{"id":20,"empresa":"GRIMALDI"},{"id":24,"empresa":"MERANOL S.A."},{"id":25,"empresa":"SIDERAR"},{"id":26,"empresa":"BBC NORDKAP"},{"id":27,"empresa":"ANTIVARI"},{"id":28,"empresa":"PETROLERA DEL CONOSUR"},{"id":29,"empresa":"PROPANEROS"},{"id":30,"empresa":"ARENERA TIMOR"},{"id":31,"empresa":"CINTRA SRL"}]